lull/__init__.py
lull/_modidx.py
lull/core.py
lull-0.0.1.dist-info/LICENSE
lull-0.0.1.dist-info/METADATA
lull-0.0.1.dist-info/WHEEL
lull-0.0.1.dist-info/entry_points.txt
lull-0.0.1.dist-info/top_level.txt
lull-0.0.1.dist-info/RECORD
